pelican/plugins/series/__init__.py
pelican/plugins/series/series.py
pelican/plugins/series/test_series.py
pelican_series_plugin-1.1.1.dist-info/WHEEL
pelican_series_plugin-1.1.1.dist-info/METADATA
pelican_series_plugin-1.1.1.dist-info/RECORD
