Metadata-Version: 2.1
Name: pelican-series-plugin
Version: 1.1.1
Summary: An installable version of the original Pelican Series plugin
Home-page: https://github.com/johanvergeer/pelican-series-plugin
License: MIT
Keywords: pelican,plugin
Author: Johan Vergeer
Author-email: johanvergeer@gmail.com
Requires-Python: >=3.8,<4.0
Classifier: Development Status :: 4 - Beta
Classifier: Environment :: Console
Classifier: Framework :: Pelican
Classifier: Framework :: Pelican :: Plugins
Classifier: Intended Audience :: End Users/Desktop
Classifier: License :: OSI Approved :: MIT License
Classifier: Operating System :: OS Independent
Classifier: Programming Language :: Python
Classifier: Programming Language :: Python :: 3
Classifier: Programming Language :: Python :: 3.8
Classifier: Programming Language :: Python :: 3.9
Classifier: Topic :: Internet :: WWW/HTTP
Classifier: Topic :: Software Development :: Libraries :: Python Modules
Provides-Extra: markdown
Requires-Dist: markdown (>=3.3.4,<4.0.0); extra == "markdown"
Requires-Dist: pelican (>=4.2,<5.0)
Project-URL: Documentation, https://docs.getpelican.com/
Project-URL: Funding, https://donate.getpelican.com/
Project-URL: Repository, https://github.com/johanvergeer/pelican-series-plugin
Project-URL: Source, https://github.com/johanvergeer/pelican-series-plugin
Project-URL: Tracker, https://github.com/johanvergeer/pelican-series-plugin/issues
